dwfpy/__init__.py
dwfpy/analog_input.py
dwfpy/analog_io.py
dwfpy/analog_output.py
dwfpy/analog_recorder.py
dwfpy/application.py
dwfpy/bindings.py
dwfpy/configuration.py
dwfpy/constants.py
dwfpy/device.py
dwfpy/device_info.py
dwfpy/digital_input.py
dwfpy/digital_io.py
dwfpy/digital_output.py
dwfpy/digital_recorder.py
dwfpy/exceptions.py
dwfpy/helpers.py
dwfpy/protocols.py
dwfpy-1.2.0.dist-info/LICENSE
dwfpy-1.2.0.dist-info/METADATA
dwfpy-1.2.0.dist-info/WHEEL
dwfpy-1.2.0.dist-info/top_level.txt
dwfpy-1.2.0.dist-info/RECORD
