Metadata-Version: 2.2
Name: dwfpy
Version: 1.2.0
Summary: Python Bindings for Digilent WaveForms API
Home-page: https://github.com/mariusgreuel/dwfpy
Author: Marius Greuel
Author-email: greuelm@mgtek.com
License: MIT
Project-URL: Bug Tracker, https://github.com/mariusgreuel/dwfpy/issues
Keywords: digilent,waveforms,analog discovery,digital discovery,ad2,ad3
Classifier: Programming Language :: Python :: 3
Classifier: License :: OSI Approved :: MIT License
Classifier: Operating System :: OS Independent
Requires-Python: >=3.8
License-File: LICENSE
Requires-Dist: numpy
